pyS7/__init__.py
pyS7/address_parser.py
pyS7/client.py
pyS7/constants.py
pyS7/errors.py
pyS7/py.typed
pyS7/requests.py
pyS7/responses.py
pyS7/tag.py
pys7-2.6.0.dist-info/licenses/LICENSE
pys7-2.6.0.dist-info/METADATA
pys7-2.6.0.dist-info/WHEEL
pys7-2.6.0.dist-info/top_level.txt
pys7-2.6.0.dist-info/RECORD
