Metadata-Version: 2.4
Name: pys7
Version: 2.6.0
Summary: Lightweight Python library for Siemens S7 over ISO-on-TCP (RFC1006).
Author-email: Alessandro <xtimmy86x@gmail.com>
License: MIT
Project-URL: Homepage, https://github.com/xtimmy86x/pyS7
Project-URL: Issues, https://github.com/xtimmy86x/pyS7/issues
Keywords: s7,siemens,plc,industrial,automation,rfc1006,iso-on-tcp
Classifier: Development Status :: 5 - Production/Stable
Classifier: Intended Audience :: Developers
Classifier: Intended Audience :: Manufacturing
Classifier: License :: OSI Approved :: MIT License
Classifier: Programming Language :: Python :: 3 :: Only
Classifier: Programming Language :: Python :: 3.8
Classifier: Programming Language :: Python :: 3.9
Classifier: Programming Language :: Python :: 3.10
Classifier: Programming Language :: Python :: 3.11
Classifier: Programming Language :: Python :: 3.12
Classifier: Topic :: Software Development :: Libraries :: Python Modules
Classifier: Topic :: System :: Networking
Classifier: Topic :: System :: Hardware
Classifier: Topic :: Scientific/Engineering :: Interface Engine/Protocol Translator
Classifier: Topic :: Home Automation
Requires-Python: >=3.8
License-File: LICENSE
Provides-Extra: dev
Requires-Dist: black>=23.7.0; extra == "dev"
Requires-Dist: mypy>=1.4.1; extra == "dev"
Requires-Dist: pytest>=7.4.0; extra == "dev"
Requires-Dist: pytest-cov>=4.1.0; extra == "dev"
Requires-Dist: ruff>=0.1.0; extra == "dev"
Dynamic: license-file
